LICENSE.txt
README.md
botanalytics/.env
botanalytics/__init__.py
botanalytics/rasa.py
botanalytics/universal.py
botanalytics-3.0.0.dist-info/LICENSE.txt
botanalytics-3.0.0.dist-info/METADATA
botanalytics-3.0.0.dist-info/WHEEL
botanalytics-3.0.0.dist-info/RECORD
